biospat/__init__.py
biospat/biospat.py
biospat/common.py
biospat/foliummap.py
biospat/mapping.py
biospat-0.0.2.dist-info/licenses/LICENSE
biospat-0.0.2.dist-info/METADATA
biospat-0.0.2.dist-info/WHEEL
biospat-0.0.2.dist-info/entry_points.txt
biospat-0.0.2.dist-info/top_level.txt
biospat-0.0.2.dist-info/RECORD
